intan_importer-0.2.0.dist-info/METADATA
intan_importer-0.2.0.dist-info/WHEEL
intan_importer-0.2.0.dist-info/licenses/LICENSE
intan_importer/__init__.py
intan_importer/_lib.abi3.so
intan_importer/_lib.py
intan_importer/core.py
intan_importer/io.py
intan_importer-0.2.0.dist-info/RECORD
