Metadata-Version: 2.4
Name: intan-importer
Version: 0.2.0
Classifier: Development Status :: 3 - Alpha
Classifier: Intended Audience :: Science/Research
Classifier: License :: OSI Approved :: MIT License
Classifier: Programming Language :: Python :: 3
Classifier: Programming Language :: Python :: 3.9
Classifier: Programming Language :: Python :: 3.10
Classifier: Programming Language :: Python :: 3.11
Classifier: Programming Language :: Python :: 3.12
Classifier: Programming Language :: Python :: 3.13
Classifier: Programming Language :: Rust
Classifier: Topic :: Scientific/Engineering
Requires-Dist: numpy>=1.20
License-File: LICENSE
Summary: Fast Python bindings for reading Intan RHS files
Author: JB
License: MIT
Requires-Python: >=3.9
Project-URL: Repository, https://github.com/brant01/python-intan-importer
Project-URL: Issues, https://github.com/brant01/python-intan-importer/issues
